{
    "metadata": {
        "timestamp": "2025-03-05T09:53:48.694080",
        "n_nodes": 45,
        "max_resources": 6
    },
    "graph": {
        "nodes": [
            {
                "id": 0,
                "x": 65.172329930871,
                "y": 37.82669626801584
            },
            {
                "id": 1,
                "x": 83.61553476876654,
                "y": 31.965915063767646
            },
            {
                "id": 2,
                "x": 4.707374306383438,
                "y": 92.98819284697072
            },
            {
                "id": 3,
                "x": 86.44135048714679,
                "y": 58.52496810932374
            },
            {
                "id": 4,
                "x": 76.54385462832725,
                "y": 37.71279253788866
            },
            {
                "id": 5,
                "x": 38.34425704824973,
                "y": 98.98179475973139
            },
            {
                "id": 6,
                "x": 53.181503217435534,
                "y": 74.11831316201695
            },
            {
                "id": 7,
                "x": 69.10171206053207,
                "y": 77.81932944907486
            },
            {
                "id": 8,
                "x": 61.89809675761947,
                "y": 49.11999281548491
            },
            {
                "id": 9,
                "x": 68.71119715617073,
                "y": 68.01408473473693
            },
            {
                "id": 10,
                "x": 58.61391548245801,
                "y": 64.71022881995778
            },
            {
                "id": 11,
                "x": 85.33893104922755,
                "y": 26.69832326845134
            },
            {
                "id": 12,
                "x": 86.57018137708043,
                "y": 5.528588042198502
            },
            {
                "id": 13,
                "x": 88.03997339323921,
                "y": 32.68691352796258
            },
            {
                "id": 14,
                "x": 53.57579996768192,
                "y": 33.530880848294544
            },
            {
                "id": 15,
                "x": 0.21945537727597886,
                "y": 51.15152103447422
            },
            {
                "id": 16,
                "x": 2.943736008844111,
                "y": 96.27141927042167
            },
            {
                "id": 17,
                "x": 62.82902658227641,
                "y": 71.39393236721334
            },
            {
                "id": 18,
                "x": 62.62044876974717,
                "y": 75.73002146014893
            },
            {
                "id": 19,
                "x": 11.399260212915351,
                "y": 97.78104338852893
            },
            {
                "id": 20,
                "x": 52.83249897004135,
                "y": 33.123779242847895
            },
            {
                "id": 21,
                "x": 64.2902083026524,
                "y": 50.476965311709876
            },
            {
                "id": 22,
                "x": 47.670159702654516,
                "y": 37.665395783382436
            },
            {
                "id": 23,
                "x": 54.085923771340795,
                "y": 47.10482006383616
            },
            {
                "id": 24,
                "x": 86.8018350342575,
                "y": 83.92509504778879
            },
            {
                "id": 25,
                "x": 26.244305641164868,
                "y": 76.86802991956357
            },
            {
                "id": 26,
                "x": 2.6491569586505337,
                "y": 23.1097370757793
            },
            {
                "id": 27,
                "x": 93.04998843153341,
                "y": 19.022470121179524
            },
            {
                "id": 28,
                "x": 41.5184224611529,
                "y": 94.47136935901945
            },
            {
                "id": 29,
                "x": 1.985288652608952,
                "y": 2.5114824371565647
            },
            {
                "id": 30,
                "x": 51.725185454770326,
                "y": 66.51323776939935
            },
            {
                "id": 31,
                "x": 45.50458397771904,
                "y": 18.2513850072211
            },
            {
                "id": 32,
                "x": 44.2737482979371,
                "y": 15.88559001382257
            },
            {
                "id": 33,
                "x": 73.79439573901006,
                "y": 44.39936807636469
            },
            {
                "id": 34,
                "x": 8.678289417633122,
                "y": 16.108179207986527
            },
            {
                "id": 35,
                "x": 79.14735247602233,
                "y": 84.2074006047576
            },
            {
                "id": 36,
                "x": 21.667917556301084,
                "y": 9.242121611177012
            },
            {
                "id": 37,
                "x": 32.6160869568358,
                "y": 46.146500312673986
            },
            {
                "id": 38,
                "x": 30.916722673768238,
                "y": 20.82235349662782
            },
            {
                "id": 39,
                "x": 7.781707892683443,
                "y": 23.173410326677978
            },
            {
                "id": 40,
                "x": 2.590590638924195,
                "y": 45.94349193519034
            },
            {
                "id": 41,
                "x": 39.10101059162561,
                "y": 45.377531910721025
            },
            {
                "id": 42,
                "x": 67.32698813953654,
                "y": 78.4714878655137
            },
            {
                "id": 43,
                "x": 77.80579790460168,
                "y": 44.34916439116018
            },
            {
                "id": 44,
                "x": 45.501621050590124,
                "y": 23.441877816640154
            }
        ],
        "edges": [
            {
                "source": 0,
                "target": 33,
                "weight": 10.841588144738958
            },
            {
                "source": 0,
                "target": 4,
                "weight": 11.372095145776541
            },
            {
                "source": 0,
                "target": 8,
                "weight": 11.758365098171504
            },
            {
                "source": 0,
                "target": 14,
                "weight": 12.366629989914692
            },
            {
                "source": 1,
                "target": 13,
                "weight": 4.482800009714585
            },
            {
                "source": 1,
                "target": 11,
                "weight": 5.5423477030578425
            },
            {
                "source": 1,
                "target": 4,
                "weight": 9.112368556596188
            },
            {
                "source": 1,
                "target": 12,
                "weight": 26.60192091983981
            },
            {
                "source": 1,
                "target": 43,
                "weight": 13.678373672889762
            },
            {
                "source": 2,
                "target": 16,
                "weight": 3.7269284662029625
            },
            {
                "source": 2,
                "target": 19,
                "weight": 8.231206065927111
            },
            {
                "source": 2,
                "target": 25,
                "weight": 26.901655416075087
            },
            {
                "source": 3,
                "target": 43,
                "weight": 16.59898127783152
            },
            {
                "source": 3,
                "target": 33,
                "weight": 18.959906136174595
            },
            {
                "source": 3,
                "target": 9,
                "weight": 20.109740711173146
            },
            {
                "source": 4,
                "target": 43,
                "weight": 6.755289202353122
            },
            {
                "source": 4,
                "target": 33,
                "weight": 7.229786761432963
            },
            {
                "source": 4,
                "target": 13,
                "weight": 12.546720945305843
            },
            {
                "source": 5,
                "target": 28,
                "weight": 5.515366113310902
            },
            {
                "source": 5,
                "target": 25,
                "weight": 25.20768572201854
            },
            {
                "source": 5,
                "target": 19,
                "weight": 26.97173814035025
            },
            {
                "source": 6,
                "target": 30,
                "weight": 7.743257270248214
            },
            {
                "source": 6,
                "target": 18,
                "weight": 9.575557256774726
            },
            {
                "source": 6,
                "target": 17,
                "weight": 10.024817095101806
            },
            {
                "source": 6,
                "target": 28,
                "weight": 23.457927216314577
            },
            {
                "source": 7,
                "target": 42,
                "weight": 1.8907552977278017
            },
            {
                "source": 7,
                "target": 18,
                "weight": 6.8096976230274375
            },
            {
                "source": 7,
                "target": 17,
                "weight": 8.979549586071334
            },
            {
                "source": 7,
                "target": 9,
                "weight": 9.813018179876172
            },
            {
                "source": 7,
                "target": 24,
                "weight": 18.72364085404976
            },
            {
                "source": 7,
                "target": 35,
                "weight": 11.904719419095827
            },
            {
                "source": 8,
                "target": 21,
                "weight": 2.75019490207346
            },
            {
                "source": 8,
                "target": 23,
                "weight": 8.067897370847618
            },
            {
                "source": 9,
                "target": 17,
                "weight": 6.7840475145111245
            },
            {
                "source": 9,
                "target": 18,
                "weight": 9.830203225634905
            },
            {
                "source": 9,
                "target": 10,
                "weight": 10.62405577469903
            },
            {
                "source": 10,
                "target": 30,
                "weight": 7.120775425902182
            },
            {
                "source": 10,
                "target": 17,
                "weight": 7.9018386905459455
            },
            {
                "source": 11,
                "target": 13,
                "weight": 6.569539028003174
            },
            {
                "source": 11,
                "target": 27,
                "weight": 10.880217253883133
            },
            {
                "source": 11,
                "target": 12,
                "weight": 21.205510296135017
            },
            {
                "source": 12,
                "target": 27,
                "weight": 14.969059857732674
            },
            {
                "source": 13,
                "target": 27,
                "weight": 14.553943256077062
            },
            {
                "source": 14,
                "target": 20,
                "weight": 0.847483386415746
            },
            {
                "source": 14,
                "target": 22,
                "weight": 7.209077658645227
            },
            {
                "source": 15,
                "target": 40,
                "weight": 5.722398931219254
            },
            {
                "source": 15,
                "target": 26,
                "weight": 28.146848799832885
            },
            {
                "source": 15,
                "target": 39,
                "weight": 28.982103820883836
            },
            {
                "source": 16,
                "target": 19,
                "weight": 8.589228984234015
            },
            {
                "source": 16,
                "target": 25,
                "weight": 30.321742421761023
            },
            {
                "source": 17,
                "target": 18,
                "weight": 4.341102777607841
            },
            {
                "source": 17,
                "target": 30,
                "weight": 12.129157742482626
            },
            {
                "source": 17,
                "target": 42,
                "weight": 8.385907822180705
            },
            {
                "source": 18,
                "target": 42,
                "weight": 5.446755997024366
            },
            {
                "source": 19,
                "target": 25,
                "weight": 25.646237660130936
            },
            {
                "source": 20,
                "target": 22,
                "weight": 6.875756504768109
            },
            {
                "source": 20,
                "target": 44,
                "weight": 12.144174994486082
            },
            {
                "source": 21,
                "target": 23,
                "weight": 10.747036166716972
            },
            {
                "source": 21,
                "target": 33,
                "weight": 11.281257331543065
            },
            {
                "source": 22,
                "target": 23,
                "weight": 11.41335881024798
            },
            {
                "source": 22,
                "target": 37,
                "weight": 17.27872218288064
            },
            {
                "source": 22,
                "target": 41,
                "weight": 11.528545447438221
            },
            {
                "source": 23,
                "target": 37,
                "weight": 21.491213776493442
            },
            {
                "source": 23,
                "target": 41,
                "weight": 15.084135618837884
            },
            {
                "source": 24,
                "target": 35,
                "weight": 7.6596866555898835
            },
            {
                "source": 24,
                "target": 42,
                "weight": 20.2240325571184
            },
            {
                "source": 25,
                "target": 28,
                "weight": 23.306140908596262
            },
            {
                "source": 26,
                "target": 39,
                "weight": 5.132945876718562
            },
            {
                "source": 26,
                "target": 34,
                "weight": 9.239710535726124
            },
            {
                "source": 26,
                "target": 29,
                "weight": 20.608949883128677
            },
            {
                "source": 26,
                "target": 40,
                "weight": 22.83382996769231
            },
            {
                "source": 29,
                "target": 34,
                "weight": 15.154749167126194
            },
            {
                "source": 29,
                "target": 36,
                "weight": 20.80161975066643
            },
            {
                "source": 31,
                "target": 32,
                "weight": 2.666822532793252
            },
            {
                "source": 31,
                "target": 44,
                "weight": 5.190493655093713
            },
            {
                "source": 31,
                "target": 38,
                "weight": 14.812682957412793
            },
            {
                "source": 32,
                "target": 44,
                "weight": 7.655400502633257
            },
            {
                "source": 32,
                "target": 38,
                "weight": 14.240146319819292
            },
            {
                "source": 33,
                "target": 43,
                "weight": 4.011716309028
            },
            {
                "source": 34,
                "target": 39,
                "weight": 7.121892247949778
            },
            {
                "source": 34,
                "target": 36,
                "weight": 14.692623526912413
            },
            {
                "source": 35,
                "target": 42,
                "weight": 13.13855806393859
            },
            {
                "source": 36,
                "target": 38,
                "weight": 14.820329504491395
            },
            {
                "source": 36,
                "target": 39,
                "weight": 19.669967567248108
            },
            {
                "source": 37,
                "target": 41,
                "weight": 6.530355805946376
            },
            {
                "source": 38,
                "target": 44,
                "weight": 14.81827143513567
            },
            {
                "source": 39,
                "target": 40,
                "weight": 23.354321116242915
            }
        ]
    },
    "configuration": {
        "start_node": 24,
        "extraction_nodes": [
            41,
            9
        ]
    }
}