{
    "metadata": {
        "timestamp": "2025-03-04T20:51:43.684751",
        "n_nodes": 35,
        "max_resources": 15
    },
    "graph": {
        "nodes": [
            {
                "id": 0,
                "x": 39.87220542656065,
                "y": 94.89946677312933
            },
            {
                "id": 1,
                "x": 95.3946711014822,
                "y": 65.86904351840919
            },
            {
                "id": 2,
                "x": 10.408450339217678,
                "y": 52.4425839296856
            },
            {
                "id": 3,
                "x": 38.23638294019729,
                "y": 20.292532978545562
            },
            {
                "id": 4,
                "x": 49.77664770285843,
                "y": 40.40921218931505
            },
            {
                "id": 5,
                "x": 79.3021242204996,
                "y": 79.31988031560438
            },
            {
                "id": 6,
                "x": 16.46099518850531,
                "y": 62.259577776085095
            },
            {
                "id": 7,
                "x": 24.750263779130577,
                "y": 52.04523262027993
            },
            {
                "id": 8,
                "x": 67.27003342599356,
                "y": 38.13058549798621
            },
            {
                "id": 9,
                "x": 92.70700304615295,
                "y": 41.042027400184466
            },
            {
                "id": 10,
                "x": 58.306524673897044,
                "y": 38.34669435835634
            },
            {
                "id": 11,
                "x": 81.0707170038292,
                "y": 81.64304305986938
            },
            {
                "id": 12,
                "x": 10.893122747940087,
                "y": 2.680572137740378
            },
            {
                "id": 13,
                "x": 20.174321156670104,
                "y": 42.33538474832732
            },
            {
                "id": 14,
                "x": 77.25311342072455,
                "y": 88.63783812157811
            },
            {
                "id": 15,
                "x": 23.042172839867913,
                "y": 92.80913737397441
            },
            {
                "id": 16,
                "x": 55.93113896262998,
                "y": 54.62658618587894
            },
            {
                "id": 17,
                "x": 40.11521044278098,
                "y": 39.427129973174345
            },
            {
                "id": 18,
                "x": 57.44251518468788,
                "y": 75.25829450200963
            },
            {
                "id": 19,
                "x": 52.19688800126515,
                "y": 76.42621138084449
            },
            {
                "id": 20,
                "x": 99.85199201590285,
                "y": 41.98007190274608
            },
            {
                "id": 21,
                "x": 5.46822575859035,
                "y": 99.15362505354607
            },
            {
                "id": 22,
                "x": 12.369092679794791,
                "y": 10.777120186616395
            },
            {
                "id": 23,
                "x": 30.634032742282702,
                "y": 22.322753775342786
            },
            {
                "id": 24,
                "x": 71.36201611856269,
                "y": 67.0301590002546
            },
            {
                "id": 25,
                "x": 59.858538891672275,
                "y": 92.02713003349496
            },
            {
                "id": 26,
                "x": 88.19041343190646,
                "y": 20.672752963031083
            },
            {
                "id": 27,
                "x": 9.59533706438387,
                "y": 85.45257682319176
            },
            {
                "id": 28,
                "x": 61.77630101949383,
                "y": 22.997095307044745
            },
            {
                "id": 29,
                "x": 43.121322244789525,
                "y": 51.3976170946831
            },
            {
                "id": 30,
                "x": 56.0057033325369,
                "y": 22.549564777223896
            },
            {
                "id": 31,
                "x": 72.65351268524972,
                "y": 97.94212537633135
            },
            {
                "id": 32,
                "x": 16.435934403711517,
                "y": 90.64159266250111
            },
            {
                "id": 33,
                "x": 37.39331221093952,
                "y": 35.63948398258934
            },
            {
                "id": 34,
                "x": 50.129598612016835,
                "y": 92.13553376570371
            }
        ],
        "edges": [
            {
                "source": 0,
                "target": 34,
                "weight": 10.623250003204287
            },
            {
                "source": 0,
                "target": 15,
                "weight": 16.959347683979793
            },
            {
                "source": 0,
                "target": 25,
                "weight": 20.19167758569095
            },
            {
                "source": 1,
                "target": 5,
                "weight": 20.973675778494407
            },
            {
                "source": 1,
                "target": 11,
                "weight": 21.30715191023091
            },
            {
                "source": 1,
                "target": 24,
                "weight": 24.06068774350033
            },
            {
                "source": 1,
                "target": 9,
                "weight": 24.97207017670396
            },
            {
                "source": 1,
                "target": 20,
                "weight": 24.3012484162458
            },
            {
                "source": 2,
                "target": 6,
                "weight": 11.532851656588836
            },
            {
                "source": 2,
                "target": 13,
                "weight": 14.054455098466759
            },
            {
                "source": 2,
                "target": 7,
                "weight": 14.347316850489944
            },
            {
                "source": 3,
                "target": 23,
                "weight": 7.868768964423844
            },
            {
                "source": 3,
                "target": 33,
                "weight": 15.370090220133763
            },
            {
                "source": 3,
                "target": 30,
                "weight": 17.912089206618575
            },
            {
                "source": 3,
                "target": 12,
                "weight": 32.524376129290054
            },
            {
                "source": 3,
                "target": 22,
                "weight": 27.561926384357157
            },
            {
                "source": 4,
                "target": 10,
                "weight": 8.775692619051641
            },
            {
                "source": 4,
                "target": 17,
                "weight": 9.711223167535222
            },
            {
                "source": 4,
                "target": 29,
                "weight": 12.846727183105305
            },
            {
                "source": 4,
                "target": 8,
                "weight": 17.64116446430972
            },
            {
                "source": 4,
                "target": 16,
                "weight": 15.492304090249956
            },
            {
                "source": 4,
                "target": 33,
                "weight": 13.27016597753975
            },
            {
                "source": 5,
                "target": 11,
                "weight": 2.919761217905744
            },
            {
                "source": 5,
                "target": 14,
                "weight": 9.54058608951786
            },
            {
                "source": 5,
                "target": 24,
                "weight": 14.631560637177667
            },
            {
                "source": 6,
                "target": 7,
                "weight": 13.154650156102479
            },
            {
                "source": 6,
                "target": 13,
                "weight": 20.267270599496086
            },
            {
                "source": 7,
                "target": 13,
                "weight": 10.734076419539461
            },
            {
                "source": 8,
                "target": 10,
                "weight": 8.966113549829787
            },
            {
                "source": 8,
                "target": 28,
                "weight": 16.09980189671745
            },
            {
                "source": 9,
                "target": 20,
                "weight": 7.206302440685781
            },
            {
                "source": 9,
                "target": 26,
                "weight": 20.864010229090415
            },
            {
                "source": 10,
                "target": 28,
                "weight": 15.736884663887219
            },
            {
                "source": 10,
                "target": 16,
                "weight": 16.452274468690614
            },
            {
                "source": 10,
                "target": 30,
                "weight": 15.963805368644028
            },
            {
                "source": 11,
                "target": 14,
                "weight": 7.9687674751518704
            },
            {
                "source": 11,
                "target": 24,
                "weight": 17.54409454543946
            },
            {
                "source": 11,
                "target": 31,
                "weight": 18.344192893106964
            },
            {
                "source": 12,
                "target": 22,
                "weight": 8.229980409909686
            },
            {
                "source": 12,
                "target": 23,
                "weight": 27.848138661126015
            },
            {
                "source": 13,
                "target": 33,
                "weight": 18.4750843026932
            },
            {
                "source": 14,
                "target": 31,
                "weight": 10.379117893383041
            },
            {
                "source": 15,
                "target": 32,
                "weight": 6.952743081085764
            },
            {
                "source": 15,
                "target": 27,
                "weight": 15.327634374233
            },
            {
                "source": 15,
                "target": 21,
                "weight": 18.684114641367962
            },
            {
                "source": 16,
                "target": 29,
                "weight": 13.210512697717789
            },
            {
                "source": 17,
                "target": 33,
                "weight": 4.664224708833862
            },
            {
                "source": 17,
                "target": 29,
                "weight": 12.342174447494331
            },
            {
                "source": 17,
                "target": 23,
                "weight": 19.5563906615043
            },
            {
                "source": 18,
                "target": 19,
                "weight": 5.374070559950884
            },
            {
                "source": 18,
                "target": 24,
                "weight": 16.169561530337905
            },
            {
                "source": 18,
                "target": 25,
                "weight": 16.94198971888235
            },
            {
                "source": 19,
                "target": 34,
                "weight": 15.844762390466373
            },
            {
                "source": 19,
                "target": 25,
                "weight": 17.38072372408852
            },
            {
                "source": 20,
                "target": 26,
                "weight": 24.289797353404595
            },
            {
                "source": 21,
                "target": 32,
                "weight": 13.883275130546973
            },
            {
                "source": 21,
                "target": 27,
                "weight": 14.309149881837966
            },
            {
                "source": 22,
                "target": 23,
                "weight": 21.608093170185168
            },
            {
                "source": 23,
                "target": 33,
                "weight": 14.933960035703807
            },
            {
                "source": 25,
                "target": 34,
                "weight": 9.729544199717624
            },
            {
                "source": 25,
                "target": 31,
                "weight": 14.096046406142039
            },
            {
                "source": 26,
                "target": 28,
                "weight": 26.516181887061833
            },
            {
                "source": 27,
                "target": 32,
                "weight": 8.586015218913824
            },
            {
                "source": 28,
                "target": 30,
                "weight": 5.787925469443637
            }
        ]
    },
    "configuration": {
        "start_node": 5,
        "extraction_nodes": [
            0,
            9
        ]
    }
}