{
    "metadata": {
        "timestamp": "2025-03-04T15:56:47.209137",
        "n_nodes": 39,
        "max_resources": 10
    },
    "graph": {
        "nodes": [
            {
                "id": 0,
                "x": 43.50111314869501,
                "y": 56.73796253891816
            },
            {
                "id": 1,
                "x": 88.00319956493891,
                "y": 41.44702994360689
            },
            {
                "id": 2,
                "x": 22.6669178371797,
                "y": 12.939785028171357
            },
            {
                "id": 3,
                "x": 31.723142862151054,
                "y": 16.089305415229404
            },
            {
                "id": 4,
                "x": 64.70882656617736,
                "y": 24.682940514258654
            },
            {
                "id": 5,
                "x": 6.10867314542628,
                "y": 5.137142964726127
            },
            {
                "id": 6,
                "x": 40.075807466977665,
                "y": 73.15837878703124
            },
            {
                "id": 7,
                "x": 2.1987706203498325,
                "y": 7.986471584626587
            },
            {
                "id": 8,
                "x": 84.16655909751022,
                "y": 31.110350234473238
            },
            {
                "id": 9,
                "x": 82.087339687762,
                "y": 57.32515719489268
            },
            {
                "id": 10,
                "x": 78.33191734706895,
                "y": 89.13741318799185
            },
            {
                "id": 11,
                "x": 17.790918734670026,
                "y": 36.651768876386924
            },
            {
                "id": 12,
                "x": 13.189460558161848,
                "y": 6.592065355854892
            },
            {
                "id": 13,
                "x": 86.58456839059286,
                "y": 35.25651128924998
            },
            {
                "id": 14,
                "x": 16.979973089408507,
                "y": 20.42145415498162
            },
            {
                "id": 15,
                "x": 39.895728469479096,
                "y": 24.945043804532187
            },
            {
                "id": 16,
                "x": 14.04280474184343,
                "y": 3.8642234234490536
            },
            {
                "id": 17,
                "x": 78.94291703361354,
                "y": 68.73424723354155
            },
            {
                "id": 18,
                "x": 80.4759374796496,
                "y": 76.89896814472218
            },
            {
                "id": 19,
                "x": 81.97978659853187,
                "y": 26.46890258292406
            },
            {
                "id": 20,
                "x": 49.297006501190424,
                "y": 97.4400668349543
            },
            {
                "id": 21,
                "x": 82.61612102885722,
                "y": 43.727226282397325
            },
            {
                "id": 22,
                "x": 92.07553770438851,
                "y": 52.18139117429176
            },
            {
                "id": 23,
                "x": 23.218053544938932,
                "y": 32.644443746346475
            },
            {
                "id": 24,
                "x": 14.510646665657456,
                "y": 34.0076304304972
            },
            {
                "id": 25,
                "x": 89.25828484107173,
                "y": 95.55825376129131
            },
            {
                "id": 26,
                "x": 97.97678087059867,
                "y": 28.841768698018853
            },
            {
                "id": 27,
                "x": 0.9845151224284754,
                "y": 50.33237599496263
            },
            {
                "id": 28,
                "x": 41.930684141591115,
                "y": 84.12642446803086
            },
            {
                "id": 29,
                "x": 30.49857389352997,
                "y": 21.005857002490767
            },
            {
                "id": 30,
                "x": 20.68531660001932,
                "y": 59.12857131841041
            },
            {
                "id": 31,
                "x": 65.77914320104405,
                "y": 6.421845361798473
            },
            {
                "id": 32,
                "x": 48.23582166812784,
                "y": 56.26533182157553
            },
            {
                "id": 33,
                "x": 61.82947000404862,
                "y": 53.597727681846976
            },
            {
                "id": 34,
                "x": 76.68598431615897,
                "y": 91.53087686771408
            },
            {
                "id": 35,
                "x": 8.447970575299923,
                "y": 65.543790873126
            },
            {
                "id": 36,
                "x": 36.5164454514391,
                "y": 29.932036079808622
            },
            {
                "id": 37,
                "x": 12.271484462951744,
                "y": 17.98840551035341
            },
            {
                "id": 38,
                "x": 64.88053142560356,
                "y": 80.82768784481071
            }
        ],
        "edges": [
            {
                "source": 0,
                "target": 32,
                "weight": 4.758239649173381
            },
            {
                "source": 0,
                "target": 6,
                "weight": 16.773872205740126
            },
            {
                "source": 0,
                "target": 33,
                "weight": 18.595422554347955
            },
            {
                "source": 1,
                "target": 21,
                "weight": 5.849778670799889
            },
            {
                "source": 1,
                "target": 13,
                "weight": 6.350986979892762
            },
            {
                "source": 1,
                "target": 8,
                "weight": 11.025731607722314
            },
            {
                "source": 1,
                "target": 19,
                "weight": 16.143909160941043
            },
            {
                "source": 1,
                "target": 22,
                "weight": 11.48087317902459
            },
            {
                "source": 1,
                "target": 26,
                "weight": 16.073734324360647
            },
            {
                "source": 2,
                "target": 14,
                "weight": 9.397697243860764
            },
            {
                "source": 2,
                "target": 3,
                "weight": 9.588257942473788
            },
            {
                "source": 2,
                "target": 29,
                "weight": 11.24261329406419
            },
            {
                "source": 2,
                "target": 16,
                "weight": 12.519630390800689
            },
            {
                "source": 2,
                "target": 37,
                "weight": 11.556539439257781
            },
            {
                "source": 3,
                "target": 29,
                "weight": 5.0667591879930445
            },
            {
                "source": 3,
                "target": 15,
                "weight": 12.050529363014576
            },
            {
                "source": 4,
                "target": 19,
                "weight": 17.36305620995044
            },
            {
                "source": 4,
                "target": 31,
                "weight": 18.292434880739005
            },
            {
                "source": 4,
                "target": 8,
                "weight": 20.491826443057672
            },
            {
                "source": 5,
                "target": 7,
                "weight": 4.837975954857883
            },
            {
                "source": 5,
                "target": 12,
                "weight": 7.228717005704559
            },
            {
                "source": 5,
                "target": 16,
                "weight": 8.035593839152773
            },
            {
                "source": 6,
                "target": 28,
                "weight": 11.123785036511606
            },
            {
                "source": 6,
                "target": 32,
                "weight": 18.76062012674594
            },
            {
                "source": 6,
                "target": 20,
                "weight": 25.973657541540348
            },
            {
                "source": 7,
                "target": 12,
                "weight": 11.07879208397556
            },
            {
                "source": 7,
                "target": 16,
                "weight": 12.54089606740428
            },
            {
                "source": 8,
                "target": 13,
                "weight": 4.7997312876432385
            },
            {
                "source": 8,
                "target": 19,
                "weight": 5.13079041321699
            },
            {
                "source": 8,
                "target": 26,
                "weight": 13.995309486018101
            },
            {
                "source": 8,
                "target": 31,
                "weight": 30.783426323229552
            },
            {
                "source": 9,
                "target": 22,
                "weight": 11.23487554421634
            },
            {
                "source": 9,
                "target": 17,
                "weight": 11.834472076857459
            },
            {
                "source": 9,
                "target": 21,
                "weight": 13.60820836141508
            },
            {
                "source": 9,
                "target": 33,
                "weight": 20.597937151497415
            },
            {
                "source": 10,
                "target": 34,
                "weight": 2.9047829399784795
            },
            {
                "source": 10,
                "target": 18,
                "weight": 12.42482834513392
            },
            {
                "source": 10,
                "target": 25,
                "weight": 12.673306604108062
            },
            {
                "source": 10,
                "target": 38,
                "weight": 15.811113764921945
            },
            {
                "source": 11,
                "target": 24,
                "weight": 4.213271053205114
            },
            {
                "source": 11,
                "target": 23,
                "weight": 6.746291347598785
            },
            {
                "source": 11,
                "target": 14,
                "weight": 16.250561491697276
            },
            {
                "source": 11,
                "target": 30,
                "weight": 22.662395879974635
            },
            {
                "source": 11,
                "target": 35,
                "weight": 30.365105225714792
            },
            {
                "source": 12,
                "target": 16,
                "weight": 2.8582018655117425
            },
            {
                "source": 12,
                "target": 37,
                "weight": 11.43325190085535
            },
            {
                "source": 13,
                "target": 21,
                "weight": 9.354228293023311
            },
            {
                "source": 13,
                "target": 19,
                "weight": 9.920991993142193
            },
            {
                "source": 13,
                "target": 26,
                "weight": 13.074074640346625
            },
            {
                "source": 14,
                "target": 37,
                "weight": 5.299961401048113
            },
            {
                "source": 14,
                "target": 29,
                "weight": 13.531226640233703
            },
            {
                "source": 14,
                "target": 24,
                "weight": 13.808756597768589
            },
            {
                "source": 15,
                "target": 36,
                "weight": 6.024088783349757
            },
            {
                "source": 15,
                "target": 29,
                "weight": 10.18939187516404
            },
            {
                "source": 17,
                "target": 18,
                "weight": 8.307395454980746
            },
            {
                "source": 17,
                "target": 38,
                "weight": 18.547290767296992
            },
            {
                "source": 18,
                "target": 34,
                "weight": 15.114777466420716
            },
            {
                "source": 18,
                "target": 25,
                "weight": 20.62276811917794
            },
            {
                "source": 18,
                "target": 38,
                "weight": 16.082646811779444
            },
            {
                "source": 19,
                "target": 31,
                "weight": 25.77489766652138
            },
            {
                "source": 20,
                "target": 28,
                "weight": 15.215642549030628
            },
            {
                "source": 20,
                "target": 38,
                "weight": 22.777563187970074
            },
            {
                "source": 21,
                "target": 22,
                "weight": 12.686743784780232
            },
            {
                "source": 23,
                "target": 24,
                "weight": 8.813467677208797
            },
            {
                "source": 23,
                "target": 36,
                "weight": 13.572191519734844
            },
            {
                "source": 24,
                "target": 27,
                "weight": 21.200319626582704
            },
            {
                "source": 25,
                "target": 34,
                "weight": 13.201609944686348
            },
            {
                "source": 27,
                "target": 35,
                "weight": 16.94373954865355
            },
            {
                "source": 27,
                "target": 30,
                "weight": 21.575324586844342
            },
            {
                "source": 28,
                "target": 38,
                "weight": 23.185710117847748
            },
            {
                "source": 29,
                "target": 36,
                "weight": 10.765289174371429
            },
            {
                "source": 30,
                "target": 35,
                "weight": 13.816934524847431
            },
            {
                "source": 32,
                "target": 33,
                "weight": 13.852919797897437
            },
            {
                "source": 34,
                "target": 38,
                "weight": 15.935086231681401
            }
        ]
    },
    "configuration": {
        "start_node": 23,
        "extraction_nodes": [
            24,
            13
        ]
    }
}