{
    "metadata": {
        "timestamp": "2025-03-05T09:48:46.195997",
        "n_nodes": 46,
        "max_resources": 11
    },
    "graph": {
        "nodes": [
            {
                "id": 0,
                "x": 25.190233468911526,
                "y": 39.58337872450915
            },
            {
                "id": 1,
                "x": 50.88471961893071,
                "y": 71.4240512435509
            },
            {
                "id": 2,
                "x": 92.18252742698219,
                "y": 85.64467538178309
            },
            {
                "id": 3,
                "x": 12.529709849523286,
                "y": 39.04213048313251
            },
            {
                "id": 4,
                "x": 6.177740340145876,
                "y": 49.55126786659471
            },
            {
                "id": 5,
                "x": 21.526792494298665,
                "y": 41.027228834366106
            },
            {
                "id": 6,
                "x": 98.66913596488469,
                "y": 47.614549724634884
            },
            {
                "id": 7,
                "x": 84.13185025628965,
                "y": 73.87397072869778
            },
            {
                "id": 8,
                "x": 11.950610090600989,
                "y": 51.94244386276027
            },
            {
                "id": 9,
                "x": 69.20321753756788,
                "y": 16.22454485843742
            },
            {
                "id": 10,
                "x": 21.54718909557234,
                "y": 87.16010639025424
            },
            {
                "id": 11,
                "x": 14.023148750595727,
                "y": 72.05068117463715
            },
            {
                "id": 12,
                "x": 74.28545410091158,
                "y": 32.76271652846966
            },
            {
                "id": 13,
                "x": 45.850924696206164,
                "y": 91.568711747741
            },
            {
                "id": 14,
                "x": 56.7222002150004,
                "y": 90.27308542977227
            },
            {
                "id": 15,
                "x": 45.21588938759413,
                "y": 88.91566041131097
            },
            {
                "id": 16,
                "x": 26.964090571376055,
                "y": 0.7286219990651377
            },
            {
                "id": 17,
                "x": 54.247247177235266,
                "y": 77.51432732645473
            },
            {
                "id": 18,
                "x": 84.64049973988885,
                "y": 24.947146979572445
            },
            {
                "id": 19,
                "x": 80.85066461542935,
                "y": 80.76370068044949
            },
            {
                "id": 20,
                "x": 26.820940798298455,
                "y": 82.91834976916734
            },
            {
                "id": 21,
                "x": 25.2997832235902,
                "y": 36.897678930427006
            },
            {
                "id": 22,
                "x": 43.23259203489448,
                "y": 82.32356688858722
            },
            {
                "id": 23,
                "x": 85.83221171420466,
                "y": 66.00835530188967
            },
            {
                "id": 24,
                "x": 62.48148776253836,
                "y": 48.71474059102435
            },
            {
                "id": 25,
                "x": 13.468483993105329,
                "y": 88.4194126237837
            },
            {
                "id": 26,
                "x": 62.128278216682666,
                "y": 44.192780372501396
            },
            {
                "id": 27,
                "x": 3.327010485935644,
                "y": 26.28601283558327
            },
            {
                "id": 28,
                "x": 63.95390590779718,
                "y": 30.544859534332137
            },
            {
                "id": 29,
                "x": 39.332314550225064,
                "y": 62.60775272255428
            },
            {
                "id": 30,
                "x": 69.92206238188625,
                "y": 90.32711064293501
            },
            {
                "id": 31,
                "x": 46.40251642675708,
                "y": 47.67024004912648
            },
            {
                "id": 32,
                "x": 34.853135387513866,
                "y": 85.47120208037936
            },
            {
                "id": 33,
                "x": 28.0983382461484,
                "y": 60.31919275898807
            },
            {
                "id": 34,
                "x": 54.97513974887185,
                "y": 89.29681725225052
            },
            {
                "id": 35,
                "x": 36.30191169550723,
                "y": 93.56220332685014
            },
            {
                "id": 36,
                "x": 46.577044582173635,
                "y": 71.91239328222487
            },
            {
                "id": 37,
                "x": 50.619627116352994,
                "y": 36.550492901409456
            },
            {
                "id": 38,
                "x": 60.85845181700146,
                "y": 26.946831561355822
            },
            {
                "id": 39,
                "x": 92.44347023881278,
                "y": 74.54183643150955
            },
            {
                "id": 40,
                "x": 49.86387525441399,
                "y": 13.969969968566787
            },
            {
                "id": 41,
                "x": 41.71135121787499,
                "y": 59.46680699134196
            },
            {
                "id": 42,
                "x": 27.599888745569267,
                "y": 19.099792118299508
            },
            {
                "id": 43,
                "x": 49.80460545358255,
                "y": 77.82825144177345
            },
            {
                "id": 44,
                "x": 59.18788281397768,
                "y": 38.811818611422765
            },
            {
                "id": 45,
                "x": 65.35859245795962,
                "y": 55.555383761713195
            }
        ],
        "edges": [
            {
                "source": 0,
                "target": 21,
                "weight": 2.687933133968002
            },
            {
                "source": 0,
                "target": 5,
                "weight": 3.937702745790541
            },
            {
                "source": 0,
                "target": 3,
                "weight": 12.672087751269748
            },
            {
                "source": 0,
                "target": 42,
                "weight": 20.624833546150516
            },
            {
                "source": 1,
                "target": 36,
                "weight": 4.335267254626445
            },
            {
                "source": 1,
                "target": 43,
                "weight": 6.494646009529647
            },
            {
                "source": 1,
                "target": 17,
                "weight": 6.956871016940589
            },
            {
                "source": 2,
                "target": 39,
                "weight": 11.105904911656555
            },
            {
                "source": 2,
                "target": 19,
                "weight": 12.338356001303934
            },
            {
                "source": 2,
                "target": 7,
                "weight": 14.260536137778061
            },
            {
                "source": 3,
                "target": 5,
                "weight": 9.213474457607655
            },
            {
                "source": 3,
                "target": 4,
                "weight": 12.279637013875577
            },
            {
                "source": 3,
                "target": 8,
                "weight": 12.913304837391042
            },
            {
                "source": 3,
                "target": 21,
                "weight": 12.948878192374574
            },
            {
                "source": 3,
                "target": 27,
                "weight": 15.72921527014916
            },
            {
                "source": 4,
                "target": 8,
                "weight": 6.248499643943179
            },
            {
                "source": 4,
                "target": 5,
                "weight": 17.557125147752952
            },
            {
                "source": 4,
                "target": 27,
                "weight": 23.439256651175796
            },
            {
                "source": 5,
                "target": 21,
                "weight": 5.593625072566386
            },
            {
                "source": 5,
                "target": 8,
                "weight": 14.520509238486467
            },
            {
                "source": 5,
                "target": 27,
                "weight": 23.420835046485966
            },
            {
                "source": 6,
                "target": 23,
                "weight": 22.43030779618385
            },
            {
                "source": 6,
                "target": 18,
                "weight": 26.65734010624709
            },
            {
                "source": 6,
                "target": 39,
                "weight": 27.637613557017104
            },
            {
                "source": 7,
                "target": 19,
                "weight": 7.631157056295746
            },
            {
                "source": 7,
                "target": 23,
                "weight": 8.04730607905557
            },
            {
                "source": 7,
                "target": 39,
                "weight": 8.338409400531374
            },
            {
                "source": 8,
                "target": 33,
                "weight": 18.191180463507923
            },
            {
                "source": 9,
                "target": 38,
                "weight": 13.586851992670017
            },
            {
                "source": 9,
                "target": 28,
                "weight": 15.25210428115057
            },
            {
                "source": 9,
                "target": 12,
                "weight": 17.301452270640308
            },
            {
                "source": 9,
                "target": 18,
                "weight": 17.731144056651424
            },
            {
                "source": 9,
                "target": 40,
                "weight": 19.470317611149007
            },
            {
                "source": 10,
                "target": 20,
                "weight": 6.76793589320564
            },
            {
                "source": 10,
                "target": 25,
                "weight": 8.176266160200061
            },
            {
                "source": 10,
                "target": 32,
                "weight": 13.412703101610296
            },
            {
                "source": 10,
                "target": 11,
                "weight": 16.879156183268208
            },
            {
                "source": 11,
                "target": 25,
                "weight": 16.378126335069016
            },
            {
                "source": 11,
                "target": 20,
                "weight": 16.789571226710375
            },
            {
                "source": 12,
                "target": 28,
                "weight": 10.566919026522829
            },
            {
                "source": 12,
                "target": 18,
                "weight": 12.973438154897554
            },
            {
                "source": 12,
                "target": 38,
                "weight": 14.632460773322727
            },
            {
                "source": 13,
                "target": 15,
                "weight": 2.7279939950295335
            },
            {
                "source": 13,
                "target": 34,
                "weight": 9.402808353142746
            },
            {
                "source": 13,
                "target": 22,
                "weight": 9.60876523763741
            },
            {
                "source": 13,
                "target": 14,
                "weight": 10.948208938513554
            },
            {
                "source": 13,
                "target": 35,
                "weight": 9.754878674975732
            },
            {
                "source": 14,
                "target": 34,
                "weight": 2.001329514785345
            },
            {
                "source": 14,
                "target": 15,
                "weight": 11.586103380240976
            },
            {
                "source": 14,
                "target": 30,
                "weight": 13.199972725291582
            },
            {
                "source": 15,
                "target": 22,
                "weight": 6.883978893166494
            },
            {
                "source": 15,
                "target": 34,
                "weight": 9.76669074720267
            },
            {
                "source": 15,
                "target": 35,
                "weight": 10.05233104115509
            },
            {
                "source": 16,
                "target": 42,
                "weight": 18.382168829280108
            },
            {
                "source": 16,
                "target": 40,
                "weight": 26.452475018019094
            },
            {
                "source": 16,
                "target": 27,
                "weight": 34.8122360864117
            },
            {
                "source": 17,
                "target": 43,
                "weight": 4.453719101483454
            },
            {
                "source": 17,
                "target": 36,
                "weight": 9.498087854152105
            },
            {
                "source": 18,
                "target": 28,
                "weight": 21.430575125732105
            },
            {
                "source": 19,
                "target": 39,
                "weight": 13.156927337102205
            },
            {
                "source": 19,
                "target": 23,
                "weight": 15.573568272489881
            },
            {
                "source": 19,
                "target": 30,
                "weight": 14.522160889122894
            },
            {
                "source": 20,
                "target": 32,
                "weight": 8.428119887725963
            },
            {
                "source": 20,
                "target": 35,
                "weight": 14.25413721384485
            },
            {
                "source": 20,
                "target": 25,
                "weight": 14.441253244264784
            },
            {
                "source": 21,
                "target": 42,
                "weight": 17.945898149425133
            },
            {
                "source": 22,
                "target": 43,
                "weight": 7.962362798929639
            },
            {
                "source": 22,
                "target": 32,
                "weight": 8.951139648443625
            },
            {
                "source": 23,
                "target": 39,
                "weight": 10.794861716056497
            },
            {
                "source": 24,
                "target": 26,
                "weight": 4.535733810662588
            },
            {
                "source": 24,
                "target": 45,
                "weight": 7.421059925449124
            },
            {
                "source": 24,
                "target": 44,
                "weight": 10.43626836044664
            },
            {
                "source": 26,
                "target": 44,
                "weight": 6.13193889389311
            },
            {
                "source": 26,
                "target": 45,
                "weight": 11.812861036934454
            },
            {
                "source": 26,
                "target": 37,
                "weight": 13.814977667007941
            },
            {
                "source": 28,
                "target": 38,
                "weight": 4.74632924717028
            },
            {
                "source": 28,
                "target": 44,
                "weight": 9.542409995022847
            },
            {
                "source": 28,
                "target": 40,
                "weight": 21.754446164648616
            },
            {
                "source": 29,
                "target": 41,
                "weight": 3.940222779544802
            },
            {
                "source": 29,
                "target": 33,
                "weight": 11.464716756527137
            },
            {
                "source": 29,
                "target": 36,
                "weight": 11.792474260327412
            },
            {
                "source": 30,
                "target": 34,
                "weight": 14.982389684833535
            },
            {
                "source": 31,
                "target": 37,
                "weight": 11.892552257504061
            },
            {
                "source": 31,
                "target": 41,
                "weight": 12.695118063224026
            },
            {
                "source": 31,
                "target": 44,
                "weight": 15.554331358931472
            },
            {
                "source": 32,
                "target": 35,
                "weight": 8.21968697463563
            },
            {
                "source": 33,
                "target": 41,
                "weight": 13.63967315096964
            },
            {
                "source": 36,
                "target": 43,
                "weight": 6.739030118833672
            },
            {
                "source": 36,
                "target": 41,
                "weight": 13.362918470124422
            },
            {
                "source": 37,
                "target": 44,
                "weight": 8.861636398918943
            },
            {
                "source": 38,
                "target": 44,
                "weight": 11.98201646185316
            },
            {
                "source": 38,
                "target": 40,
                "weight": 17.008223028553008
            },
            {
                "source": 44,
                "target": 45,
                "weight": 17.844456602887963
            }
        ]
    },
    "configuration": {
        "start_node": 42,
        "extraction_nodes": [
            3,
            40
        ]
    }
}